mmmm/__init__.py
mmmm/__main__.py
mmmm/__version__.py
mmmm/_main.py
mmmm-1.0.2.dist-info/LICENSE
mmmm-1.0.2.dist-info/METADATA
mmmm-1.0.2.dist-info/WHEEL
mmmm-1.0.2.dist-info/entry_points.txt
mmmm-1.0.2.dist-info/top_level.txt
mmmm-1.0.2.dist-info/RECORD
