Metadata-Version: 2.1
Name: mmmm
Version: 1.0.2
Summary: Google My Maps to MAPS.ME KML converter
Home-page: https://github.com/igrmk/mmmm
Author: igrmk
Author-email: igrmkx@gmail.com
License: UNKNOWN
Platform: UNKNOWN
Classifier: Programming Language :: Python :: 3
Classifier: License :: OSI Approved :: MIT License
Classifier: Operating System :: OS Independent
Requires-Python: >=3.0
License-File: LICENSE
Requires-Dist: lxml
Requires-Dist: importlib-metadata ; python_version < "3.8"
